README.rst
setup.py
seisma/__init__.py
seisma/client.py
seisma.egg-info/PKG-INFO
seisma.egg-info/SOURCES.txt
seisma.egg-info/dependency_links.txt
seisma.egg-info/not-zip-safe
seisma.egg-info/requires.txt
seisma.egg-info/top_level.txt