Metadata-Version: 1.1
Name: seisma
Version: 0.0.3
Summary: Python binding to seisma analytic system
Home-page: https://github.com/trifonovmixail/seisma-client
Author: Mikhail Trifonov
Author-email: trifonovmixail@ya.ru
License: GNU LGPL
Keywords: client rest binding
Platform: any
Classifier: Development Status :: 3 - Alpha
Classifier: Natural Language :: Russian
Classifier: Intended Audience :: Developers
Classifier: Operating System :: OS Independent
Classifier: Programming Language :: Python
Classifier: Programming Language :: Python :: 2.7
Classifier: Programming Language :: Python :: 3
Classifier: Programming Language :: Python :: Implementation :: CPython
Classifier: Topic :: Software Development :: Testing
